Metadata-Version: 1.0
Name: DistributionGenerator
Version: 1.0
Summary: Distribution generators
Home-page: UNKNOWN
Author: UNKNOWN
Author-email: UNKNOWN
License: UNKNOWN
Platform: UNKNOWN
